internlm/__init__.py
internlm/apis/__init__.py
internlm/apis/inference.py
internlm/core/__init__.py
internlm/core/engine.py
internlm/core/gradient_handler.py
internlm/core/naive_amp.py
internlm/core/trainer.py
internlm/core/communication/__init__.py
internlm/core/communication/p2p.py
internlm/core/communication/utils.py
internlm/core/context/__init__.py
internlm/core/context/parallel_context.py
internlm/core/context/process_group_initializer.py
internlm/core/context/random.py
internlm/core/scheduler/__init__.py
internlm/core/scheduler/base_scheduler.py
internlm/core/scheduler/no_pipeline_scheduler.py
internlm/core/scheduler/pipeline_scheduler.py
internlm/data/__init__.py
internlm/data/batch_sampler.py
internlm/data/collaters.py
internlm/data/dataset.py
internlm/data/dummy_dataset.py
internlm/data/packed_dataset.py
internlm/data/single_dataset.py
internlm/data/utils.py
internlm/initialize/__init__.py
internlm/initialize/initialize_tensor.py
internlm/initialize/initialize_trainer.py
internlm/initialize/launch.py
internlm/initialize/legacy/__init__.py
internlm/initialize/legacy/launch.py
internlm/model/__init__.py
internlm/model/embedding.py
internlm/model/linear.py
internlm/model/loss.py
internlm/model/metrics.py
internlm/model/modeling_internlm.py
internlm/model/modeling_llama.py
internlm/model/modeling_moe.py
internlm/model/moe.py
internlm/model/multi_head_attention.py
internlm/model/norm.py
internlm/model/utils.py
internlm/monitor/__init__.py
internlm/monitor/alert.py
internlm/monitor/monitor.py
internlm/monitor/utils.py
internlm/solver/__init__.py
internlm/solver/beta2_scheduler.py
internlm/solver/lr_scheduler.py
internlm/solver/pipeline_utils.py
internlm/solver/optimizer/__init__.py
internlm/solver/optimizer/base_optimizer.py
internlm/solver/optimizer/fsdp_optimizer.py
internlm/solver/optimizer/hybrid_zero_optim.py
internlm/solver/optimizer/store.py
internlm/solver/optimizer/utils.py
internlm/train/__init__.py
internlm/train/training_internlm.py
Interntest-0.2.0.dist-info/LICENSE
Interntest-0.2.0.dist-info/METADATA
Interntest-0.2.0.dist-info/WHEEL
Interntest-0.2.0.dist-info/top_level.txt
Interntest-0.2.0.dist-info/RECORD
