Metadata-Version: 2.1
Name: Interntest
Version: 0.2.0
Summary: an open-sourced lightweight training framework aims to support model pre-training without the need for extensive dependencies
Classifier: Programming Language :: Python :: 3.8
Classifier: Programming Language :: Python :: 3.9
Classifier: Programming Language :: Python :: 3.10
Classifier: Programming Language :: Python :: 3.11
Classifier: Intended Audience :: Developers
Classifier: Intended Audience :: Education
Classifier: Intended Audience :: Science/Research
License-File: LICENSE
